duckcloud/__init__.py
duckcloud/Session.py
duckcloud/VM.py
duckcloud-0.2.1.dist-info/METADATA
duckcloud-0.2.1.dist-info/WHEEL
duckcloud-0.2.1.dist-info/RECORD
