Metadata-Version: 2.1
Name: duckcloud
Version: 0.2.1
Summary: A small wrapper for duckcloud.
Author: BadPythonCoder
Author-email: goaway@lol.com
Requires-Python: >=3.7,<4.0
Classifier: Programming Language :: Python :: 3
Classifier: Programming Language :: Python :: 3.7
Classifier: Programming Language :: Python :: 3.8
Classifier: Programming Language :: Python :: 3.9
Classifier: Programming Language :: Python :: 3.10
Classifier: Programming Language :: Python :: 3.11
Requires-Dist: python-socketio (>=5.8.0,<6.0.0)
Requires-Dist: requests (>=2.30.0,<3.0.0)
Requires-Dist: websocket-client (>=1.5.1,<2.0.0)
